{"objectClassName": "domain", "handle": "145190763_DOMAIN_COM-VRSN", "ldhName": "BAZURK.COM", "links": [{"value": "https://rdap.verisign.com/com/v1/domain/BAZURK.COM", "rel": "self", "href": "https://rdap.verisign.com/com/v1/domain/BAZURK.COM", "type": "application/rdap+json"}, {"value": "https://rdap.internet.bs/domain/BAZURK.COM", "rel": "related", "href": "https://rdap.internet.bs/domain/BAZURK.COM", "type": "application/rdap+json"}], "status": ["client transfer prohibited"], "entities": [{"objectClassName": "entity", "handle": "2487", "roles": ["registrar"], "publicIds": [{"type": "IANA Registrar ID", "identifier": "2487"}], "vcardArray": ["vcard", [["version", {}, "text", "4.0"], ["fn", {}, "text", "Internet Domain Service BS Corp"]]], "entities": [{"objectClassName": "entity", "roles": ["abuse"], "vcardArray": ["vcard", [["version", {}, "text", "4.0"], ["fn", {}, "text", ""], ["tel", {"type": "voice"}, "uri", "tel:+1.5163015301"], ["email", {}, "text", "abuse@internet.bs"]]]}]}], "events": [{"eventAction": "registration", "eventDate": "2005-03-05T22:54:19Z"}, {"eventAction": "expiration", "eventDate": "2024-03-05T22:54:19Z"}, {"eventAction": "last changed", "eventDate": "2022-10-17T02:34:34Z"}, {"eventAction": "last update of RDAP database", "eventDate": "2022-12-05T21:08:47Z"}], "secureDNS": {"delegationSigned": false}, "nameservers": [{"objectClassName": "nameserver", "ldhName": "DNS1.SMOOTHDNS.COM"}, {"objectClassName": "nameserver", "ldhName": "DNS2.SMOOTHDNS.COM"}], "rdapConformance": ["rdap_level_0", "icann_rdap_technical_implementation_guide_0", "icann_rdap_response_profile_0"], "notices": [{"title": "Terms of Use", "description": ["Service subject to Terms of Use."], "links": [{"href": "https://www.verisign.com/domain-names/registration-data-access-protocol/terms-service/index.xhtml", "type": "text/html"}]}, {"title": "Status Codes", "description": ["For more information on domain status codes, please visit https://icann.org/epp"], "links": [{"href": "https://icann.org/epp", "type": "text/html"}]}, {"title": "RDDS Inaccuracy Complaint Form", "description": ["URL of the ICANN RDDS Inaccuracy Complaint Form: https://icann.org/wicf"], "links": [{"href": "https://icann.org/wicf", "type": "text/html"}]}]}