{"events": [{"eventDate": "2020-08-15T18:45:01+00:00", "eventAction": "registration"}, {"eventDate": "2021-04-10T15:16:48", "eventAction": "last changed"}, {"eventDate": "2025-08-15T00:00:00+00:00", "eventAction": "soft expiration"}], "handle": "hush.is-164522", "status": ["active"], "ldhName": "hush.is", "notices": [{"links": [{"rel": "self", "href": "https://www.isnic.is/en/about/copyright", "type": "text/html", "value": "https://www.isnic.is/en/about/copyright"}], "title": "Copyright \u00a92022", "description": ["Restricted rights.\nExcept for agreed Internet operational purposes, no part of this publication may be reproduced, stored \nin a retrieval system, or transmitted, in any form or by any means, electronic, mechanical, recording, or \notherwise, without prior permission from ISNIC. Any use of this material to target advertising or similar \nactivities is explicitly forbidden and will be prosecuted. ISNIC requests to be notified of any such \nactivities or suspicions thereof."]}, {"title": "client info", "description": ["8.48.88.141/32", "2022-12-05 22:13:43.93517+00"]}], "entities": [{"roles": ["registrant", "administrative", "billing", "technical"], "events": [{"eventDate": "2020-08-15T18:24:09", "eventAction": "registration"}, {"eventDate": "2020-08-15T18:24:09", "eventActor": "ISHM-IS", "eventAction": "last changed"}], "handle": "JL2604-IS", "status": ["active", "removed"], "isnic_info": {"cc": "US"}, "vcardArray": ["vcard", [["version", {}, "text", "4.0"], ["kind", {}, "text", "person"], ["adr", {}, "text", ["", "", "", "", "", "", "United States"]]]], "objectClassName": "entity"}, {"roles": ["zone"], "events": [{"eventDate": "2012-01-19T19:38:09", "eventAction": "registration"}, {"eventDate": "2020-06-02T14:45:45", "eventActor": "CN25-IS", "eventAction": "last changed"}], "handle": "CN25-IS", "status": ["active", "removed"], "isnic_info": {"cc": "US"}, "vcardArray": ["vcard", [["version", {}, "text", "4.0"], ["kind", {}, "text", "role"], ["adr", {}, "text", ["", "", "665 3rd Street, Suite 207", "San Francisco", "CA", "94107", "United States"]], ["email", {}, "text", "noc@cloudflare.com"], ["fn", {}, "text", "CloudFlare NOC"], ["tel", {"type": ["voice"]}, "uri", "tel:+1-650-319-8930"]]], "objectClassName": "entity"}], "secureDNS": {"delegationSigned": false}, "nameservers": [{"ldhName": "chad.ns.cloudflare.com", "objectClassName": "nameserver"}, {"ldhName": "kara.ns.cloudflare.com", "objectClassName": "nameserver"}], "unicodeName": "hush.is", "objectClassName": "domain", "rdapConformance": ["rdap_level_0", "isnic_level_0"]}