{"objectClassName": "domain", "handle": "2111832238_DOMAIN_COM-VRSN", "ldhName": "MAMMOTHCIRCUS.COM", "links": [{"value": "https://rdap.verisign.com/com/v1/domain/MAMMOTHCIRCUS.COM", "rel": "self", "href": "https://rdap.verisign.com/com/v1/domain/MAMMOTHCIRCUS.COM", "type": "application/rdap+json"}, {"value": "https://rdap.gandi.net/domain/MAMMOTHCIRCUS.COM", "rel": "related", "href": "https://rdap.gandi.net/domain/MAMMOTHCIRCUS.COM", "type": "application/rdap+json"}], "status": ["client transfer prohibited"], "entities": [{"objectClassName": "entity", "handle": "81", "roles": ["registrar"], "publicIds": [{"type": "IANA Registrar ID", "identifier": "81"}], "vcardArray": ["vcard", [["version", {}, "text", "4.0"], ["fn", {}, "text", "Gandi SAS"]]], "entities": [{"objectClassName": "entity", "roles": ["abuse"], "vcardArray": ["vcard", [["version", {}, "text", "4.0"], ["fn", {}, "text", ""], ["tel", {"type": "voice"}, "uri", "tel:+33.170377661"], ["email", {}, "text", "abuse@support.gandi.net"]]]}]}], "events": [{"eventAction": "registration", "eventDate": "2017-04-06T18:30:43Z"}, {"eventAction": "expiration", "eventDate": "2023-04-06T18:30:43Z"}, {"eventAction": "last changed", "eventDate": "2022-03-18T07:54:02Z"}, {"eventAction": "last update of RDAP database", "eventDate": "2022-12-05T22:11:34Z"}], "secureDNS": {"delegationSigned": true, "dsData": [{"keyTag": 38894, "algorithm": 14, "digestType": 2, "digest": "C8CCAD2F122F62E4DBE807FC6C7EECDC4449959844A10F66E9327783C6045E74"}, {"keyTag": 47175, "algorithm": 14, "digestType": 2, "digest": "5456F5650451B401007BF6416B7FF0140F2E0282E2B8DBFB662F161667D542EA"}]}, "nameservers": [{"objectClassName": "nameserver", "ldhName": "NS1.SUAH.DEV"}, {"objectClassName": "nameserver", "ldhName": "NS2.SUAH.DEV"}, {"objectClassName": "nameserver", "ldhName": "NS3.SUAH.DEV"}, {"objectClassName": "nameserver", "ldhName": "NS4.SUAH.DEV"}], "rdapConformance": ["rdap_level_0", "icann_rdap_technical_implementation_guide_0", "icann_rdap_response_profile_0"], "notices": [{"title": "Terms of Use", "description": ["Service subject to Terms of Use."], "links": [{"href": "https://www.verisign.com/domain-names/registration-data-access-protocol/terms-service/index.xhtml", "type": "text/html"}]}, {"title": "Status Codes", "description": ["For more information on domain status codes, please visit https://icann.org/epp"], "links": [{"href": "https://icann.org/epp", "type": "text/html"}]}, {"title": "RDDS Inaccuracy Complaint Form", "description": ["URL of the ICANN RDDS Inaccuracy Complaint Form: https://icann.org/wicf"], "links": [{"href": "https://icann.org/wicf", "type": "text/html"}]}]}