{"objectClassName": "domain", "handle": "154111050_DOMAIN_CC-VRSN", "ldhName": "ONLYFEDS.CC", "links": [{"value": "https://tld-rdap.verisign.com/cc/v1/domain/ONLYFEDS.CC", "rel": "self", "href": "https://tld-rdap.verisign.com/cc/v1/domain/ONLYFEDS.CC", "type": "application/rdap+json"}, {"value": "https://rdap.dynadot.com/domain/ONLYFEDS.CC", "rel": "related", "href": "https://rdap.dynadot.com/domain/ONLYFEDS.CC", "type": "application/rdap+json"}], "status": ["client transfer prohibited"], "entities": [{"objectClassName": "entity", "handle": "472", "roles": ["registrar"], "publicIds": [{"type": "IANA Registrar ID", "identifier": "472"}], "vcardArray": ["vcard", [["version", {}, "text", "4.0"], ["fn", {}, "text", "DYNADOT, LLC"]]], "entities": [{"objectClassName": "entity", "roles": ["abuse"], "vcardArray": ["vcard", [["version", {}, "text", "4.0"], ["fn", {}, "text", ""], ["tel", {"type": "voice"}, "uri", "tel:+16502620100"], ["email", {}, "text", "abuse@dynadot.com"]]]}]}], "events": [{"eventAction": "registration", "eventDate": "2021-01-21T23:10:34Z"}, {"eventAction": "expiration", "eventDate": "2031-01-21T23:10:34Z"}, {"eventAction": "last changed", "eventDate": "2021-01-23T16:30:08Z"}, {"eventAction": "last update of RDAP database", "eventDate": "2022-12-05T22:25:56Z"}], "secureDNS": {"delegationSigned": true, "dsData": [{"keyTag": 2371, "algorithm": 13, "digestType": 2, "digest": "3409B97FB9B4434B1E1D486393AA32F25DBB870B300282F2C0CA1820001508B2"}]}, "nameservers": [{"objectClassName": "nameserver", "ldhName": "DAISY.NS.CLOUDFLARE.COM"}, {"objectClassName": "nameserver", "ldhName": "DILBERT.NS.CLOUDFLARE.COM"}], "rdapConformance": ["rdap_level_0", "icann_rdap_technical_implementation_guide_0", "icann_rdap_response_profile_0"], "notices": [{"title": "Terms of Use", "description": ["Service subject to Terms of Use."], "links": [{"href": "https://www.verisign.com/domain-names/registration-data-access-protocol/terms-service/index.xhtml", "type": "text/html"}]}, {"title": "Status Codes", "description": ["For more information on domain status codes, please visit https://icann.org/epp"], "links": [{"href": "https://icann.org/epp", "type": "text/html"}]}, {"title": "RDDS Inaccuracy Complaint Form", "description": ["URL of the ICANN RDDS Inaccuracy Complaint Form: https://icann.org/wicf"], "links": [{"href": "https://icann.org/wicf", "type": "text/html"}]}]}